<?xml version='1.0'?><NXHeader>	<Version>Tuval</Version>	<ServiceName>AMD.ENSEMBLE.ADD_SUB_INFO</ServiceName>	<ServiceQual></ServiceQual>	<ServiceVer></ServiceVer>	<DialogType></DialogType>	<DialogRef></DialogRef>	<ApplRef>1477675601ADD_DLU_SUB</ApplRef>	<ApplGroup></ApplGroup>	<CompGroup></CompGroup>	<CompName></CompName>	<AcctCode></AcctCode>	<ContentType>XML</ContentType>	<MsgSubType></MsgSubType>	<ReqSentTime></ReqSentTime>	<ReplyCompCode></ReplyCompCode>	<ReplyReasonCode></ReplyReasonCode>	<ParentDialogRef></ParentDialogRef></NXHeader><?xml version='1.0'?><request xmlns:xsi="http://www.w3.org/2001/XMLSchema-instance" xsi:noNamespaceSchemaLocation="createSubscriberRequest.xsd">	<header></header>	<createSubscriber>		<banInfo type="amdocs.APILink.datatypes.BanInfo">			<banId>194676798</banId>		</banInfo>		<subscriberApiInfo type="amdocs.APILink.datatypes.SubscriberApiInfo">			<networkInfo>				<networkInd>C</networkInd>			</networkInfo>			<resourceApiInfo>				<ptnInfo>					<numberLocation>REG</numberLocation>					<ptnType>RGL</ptnType>					<method>R</method>				</ptnInfo>				<npaNxxInfo>					<npa>303</npa>					<nxx>330</nxx>				</npaNxxInfo>				<naiInfo>					<userName>BSTDLYAPI</userName>				</naiInfo>			</resourceApiInfo>			<newPricePlanInfo>        <newPpSocInfo>          <pricePlanSocCode>DUSCX410</pricePlanSocCode>          <featureApiInfoList>            <FeatureApiInfo>              <featureCode>CHSDA</featureCode>            </FeatureApiInfo>            <FeatureApiInfo>              <featureCode>CLIP</featureCode>            </FeatureApiInfo>            <FeatureApiInfo>              <featureCode>HLT</featureCode>            </FeatureApiInfo>            <FeatureApiInfo>              <featureCode>INT</featureCode>            </FeatureApiInfo>            <FeatureApiInfo>              <featureCode>SMS</featureCode>            </FeatureApiInfo>            <FeatureApiInfo>              <featureCode>STD</featureCode>            </FeatureApiInfo>            <FeatureApiInfo>              <featureCode>TWAYR</featureCode>            </FeatureApiInfo>            <FeatureApiInfo>              <featureCode>UNTETH</featureCode>            </FeatureApiInfo>                      </featureApiInfoList>        </newPpSocInfo>        <otherSocInfoList>             <SocInfo>            <pricePlanSocCode>DUSC</pricePlanSocCode>            <featureApiInfoList>              <FeatureApiInfo>                <featureCode>GENALL</featureCode>              </FeatureApiInfo>                          </featureApiInfoList>          </SocInfo>                   <SocInfo>            <pricePlanSocCode>VMENGLISH</pricePlanSocCode>            <featureApiInfoList>              <FeatureApiInfo>                <featureCode>VMC9</featureCode>              </FeatureApiInfo>            </featureApiInfoList>          </SocInfo>        </otherSocInfoList>      </newPricePlanInfo>			<equipmentApiInfoList>				<EquipmentApiInfo>					<!--itemId>RECC190SP1</itemId-->					<serial>268400000006651114</serial>					<serialType>E</serialType>					<activateInd>Y</activateInd>				</EquipmentApiInfo>			</equipmentApiInfoList>			<memoInfo>				<memoSource>C</memoSource>			</memoInfo>		</subscriberApiInfo>		<applicationDataInfo type="amdocs.APILink.datatypes.ApplicationDataInfo">			<applicationID>API</applicationID>			<applicationUser>abc123</applicationUser>		</applicationDataInfo>	</createSubscriber></request>